<?xml version="1.0" encoding="UTF-8"?><manufacturers><architecture name="x86"><manufacturer><name>Intel</name><processors><processor><cores>4</cores><name>Core i5</name></processor><processor><cores>6</cores><name>Core i7</name></processor></processors></manufacturer></architecture><architecture name="x86"><manufacturer><name>AMD</name><processors><processor><cores>6</cores><name>Ryzen 5</name></processor><processor><cores>8</cores><name>Ryzen 7</name></processor></processors></manufacturer></architecture><architecture name="ARM"><manufacturer><name>Qualcomm</name><processors><processor><cores>8</cores><name>Snapdragon 888</name></processor><processor><cores>6</cores><name>Snapdragon 865</name></processor></processors></manufacturer></architecture><architecture name="ARM"><manufacturer><name>Apple</name><processors><processor><cores>8</cores><name>M1</name></processor><processor><cores>6</cores><name>A14 Bionic</name></processor></processors></manufacturer></architecture></manufacturers>